openbci/__init__.py
openbci/cyton.py
openbci/ganglion.py
openbci/wifi.py
openbci/plugins/__init__.py
openbci/plugins/csv_collect.py
openbci/plugins/noise_test.py
openbci/plugins/plugin_interface.py
openbci/plugins/print.py
openbci/plugins/sample_rate.py
openbci/plugins/streamer_lsl.py
openbci/plugins/streamer_osc.py
openbci/plugins/streamer_tcp_server.py
openbci/plugins/udp_server.py
openbci/utils/__init__.py
openbci/utils/constants.py
openbci/utils/parse.py
openbci/utils/ssdp.py
openbci/utils/utilities.py
openbci_py101-1.0.0.dist-info/METADATA
openbci_py101-1.0.0.dist-info/RECORD
openbci_py101-1.0.0.dist-info/WHEEL
openbci_py101-1.0.0.dist-info/top_level.txt
